{
    "16Cores": {
        "onDemand": [
            {
                "Architecture": [
                    "x86_64"
                ],
                "BestOnDemandHourPriceRegion": "us-gov-west-1",
                "CanonicalName": "c5a.4xlarge",
                "InstanceType": "c5a.4xlarge",
                "Memory": 32768,
                "ModifiedDate": "2024-07-22 00:24:51",
                "PaymentType": "OnDemand",
                "PricePerHour": 0.736,
                "tags": [
                    "cheapest"
                ]
            },
            {
                "Architecture": [
                    "x86_64"
                ],
                "BestOnDemandHourPriceRegion": "us-gov-west-1",
                "CanonicalName": "c5.4xlarge",
                "InstanceType": "c5.4xlarge",
                "Memory": 32768,
                "ModifiedDate": "2024-07-22 00:24:51",
                "PaymentType": "OnDemand",
                "PricePerHour": 0.816,
                "tags": []
            },
            {
                "Architecture": [
                    "x86_64"
                ],
                "BestOnDemandHourPriceRegion": "us-gov-west-1",
                "CanonicalName": "c6i.4xlarge",
                "InstanceType": "c6i.4xlarge",
                "Memory": 32768,
                "ModifiedDate": "2024-07-22 00:24:51",
                "PaymentType": "OnDemand",
                "PricePerHour": 0.816,
                "tags": []
            },
            {
                "Architecture": [
                    "x86_64"
                ],
                "BestOnDemandHourPriceRegion": "us-gov-west-1",
                "CanonicalName": "m5a.4xlarge",
                "InstanceType": "m5a.4xlarge",
                "Memory": 65536,
                "ModifiedDate": "2024-07-22 00:24:51",
                "PaymentType": "OnDemand",
                "PricePerHour": 0.872,
                "tags": []
            }
        ],
        "spot": [
            {
                "Architecture": [
                    "x86_64"
                ],
                "BestOnDemandHourPriceRegion": "us-gov-west-1",
                "CanonicalName": "c3.4xlarge",
                "InstanceType": "c3.4xlarge",
                "Memory": 30720,
                "ModifiedDate": "2024-07-22 00:24:51",
                "PaymentType": "OnDemand",
                "PricePerHour": 0,
                "tags": [
                    "cheapest"
                ]
            },
            {
                "Architecture": [
                    "x86_64"
                ],
                "BestOnDemandHourPriceRegion": "us-gov-west-1",
                "CanonicalName": "c4.4xlarge",
                "InstanceType": "c4.4xlarge",
                "Memory": 30720,
                "ModifiedDate": "2024-07-22 00:24:51",
                "PaymentType": "OnDemand",
                "PricePerHour": 0,
                "tags": []
            },
            {
                "Architecture": [
                    "x86_64"
                ],
                "BestOnDemandHourPriceRegion": "us-gov-west-1",
                "CanonicalName": "c5.4xlarge",
                "InstanceType": "c5.4xlarge",
                "Memory": 32768,
                "ModifiedDate": "2024-07-22 00:24:51",
                "PaymentType": "OnDemand",
                "PricePerHour": 0,
                "tags": []
            },
            {
                "Architecture": [
                    "x86_64"
                ],
                "BestOnDemandHourPriceRegion": "us-gov-west-1",
                "CanonicalName": "c5a.4xlarge",
                "InstanceType": "c5a.4xlarge",
                "Memory": 32768,
                "ModifiedDate": "2024-07-22 00:24:51",
                "PaymentType": "OnDemand",
                "PricePerHour": 0,
                "tags": []
            }
        ]
    },
    "4Cores": {
        "onDemand": [
            {
                "Architecture": [
                    "x86_64"
                ],
                "BestOnDemandHourPriceRegion": "us-gov-west-1",
                "CanonicalName": "t3a.xlarge",
                "InstanceType": "t3a.xlarge",
                "Memory": 16384,
                "ModifiedDate": "2024-07-22 00:24:51",
                "PaymentType": "OnDemand",
                "PricePerHour": 0.1757,
                "tags": [
                    "cheapest"
                ]
            },
            {
                "Architecture": [
                    "x86_64"
                ],
                "BestOnDemandHourPriceRegion": "us-gov-west-1",
                "CanonicalName": "c5a.xlarge",
                "InstanceType": "c5a.xlarge",
                "Memory": 8192,
                "ModifiedDate": "2024-07-22 00:24:51",
                "PaymentType": "OnDemand",
                "PricePerHour": 0.184,
                "tags": []
            },
            {
                "Architecture": [
                    "x86_64"
                ],
                "BestOnDemandHourPriceRegion": "us-gov-west-1",
                "CanonicalName": "t3.xlarge",
                "InstanceType": "t3.xlarge",
                "Memory": 16384,
                "ModifiedDate": "2024-07-22 00:24:51",
                "PaymentType": "OnDemand",
                "PricePerHour": 0.1952,
                "tags": []
            },
            {
                "Architecture": [
                    "x86_64"
                ],
                "BestOnDemandHourPriceRegion": "us-gov-west-1",
                "CanonicalName": "c5.xlarge",
                "InstanceType": "c5.xlarge",
                "Memory": 8192,
                "ModifiedDate": "2024-07-22 00:24:51",
                "PaymentType": "OnDemand",
                "PricePerHour": 0.204,
                "tags": []
            }
        ],
        "spot": [
            {
                "Architecture": [
                    "x86_64"
                ],
                "BestOnDemandHourPriceRegion": "us-gov-west-1",
                "CanonicalName": "c3.xlarge",
                "InstanceType": "c3.xlarge",
                "Memory": 7680,
                "ModifiedDate": "2024-07-22 00:24:51",
                "PaymentType": "OnDemand",
                "PricePerHour": 0,
                "tags": [
                    "cheapest"
                ]
            },
            {
                "Architecture": [
                    "x86_64"
                ],
                "BestOnDemandHourPriceRegion": "us-gov-west-1",
                "CanonicalName": "c4.xlarge",
                "InstanceType": "c4.xlarge",
                "Memory": 7680,
                "ModifiedDate": "2024-07-22 00:24:51",
                "PaymentType": "OnDemand",
                "PricePerHour": 0,
                "tags": []
            },
            {
                "Architecture": [
                    "x86_64"
                ],
                "BestOnDemandHourPriceRegion": "us-gov-west-1",
                "CanonicalName": "c5.xlarge",
                "InstanceType": "c5.xlarge",
                "Memory": 8192,
                "ModifiedDate": "2024-07-22 00:24:51",
                "PaymentType": "OnDemand",
                "PricePerHour": 0,
                "tags": []
            },
            {
                "Architecture": [
                    "x86_64"
                ],
                "BestOnDemandHourPriceRegion": "us-gov-west-1",
                "CanonicalName": "c5a.xlarge",
                "InstanceType": "c5a.xlarge",
                "Memory": 8192,
                "ModifiedDate": "2024-07-22 00:24:51",
                "PaymentType": "OnDemand",
                "PricePerHour": 0,
                "tags": []
            }
        ]
    },
    "8Cores": {
        "onDemand": [
            {
                "Architecture": [
                    "x86_64"
                ],
                "BestOnDemandHourPriceRegion": "us-gov-west-1",
                "CanonicalName": "t3a.2xlarge",
                "InstanceType": "t3a.2xlarge",
                "Memory": 32768,
                "ModifiedDate": "2024-07-22 00:24:51",
                "PaymentType": "OnDemand",
                "PricePerHour": 0.3514,
                "tags": [
                    "cheapest"
                ]
            },
            {
                "Architecture": [
                    "x86_64"
                ],
                "BestOnDemandHourPriceRegion": "us-gov-west-1",
                "CanonicalName": "c5a.2xlarge",
                "InstanceType": "c5a.2xlarge",
                "Memory": 16384,
                "ModifiedDate": "2024-07-22 00:24:51",
                "PaymentType": "OnDemand",
                "PricePerHour": 0.368,
                "tags": []
            },
            {
                "Architecture": [
                    "x86_64"
                ],
                "BestOnDemandHourPriceRegion": "us-gov-west-1",
                "CanonicalName": "t3.2xlarge",
                "InstanceType": "t3.2xlarge",
                "Memory": 32768,
                "ModifiedDate": "2024-07-22 00:24:51",
                "PaymentType": "OnDemand",
                "PricePerHour": 0.3904,
                "tags": []
            },
            {
                "Architecture": [
                    "x86_64"
                ],
                "BestOnDemandHourPriceRegion": "us-gov-west-1",
                "CanonicalName": "c5.2xlarge",
                "InstanceType": "c5.2xlarge",
                "Memory": 16384,
                "ModifiedDate": "2024-07-22 00:24:51",
                "PaymentType": "OnDemand",
                "PricePerHour": 0.408,
                "tags": []
            }
        ],
        "spot": [
            {
                "Architecture": [
                    "x86_64"
                ],
                "BestOnDemandHourPriceRegion": "us-gov-west-1",
                "CanonicalName": "c1.xlarge",
                "InstanceType": "c1.xlarge",
                "Memory": 7168,
                "ModifiedDate": "2024-07-22 00:24:51",
                "PaymentType": "OnDemand",
                "PricePerHour": 0,
                "tags": [
                    "cheapest"
                ]
            },
            {
                "Architecture": [
                    "x86_64"
                ],
                "BestOnDemandHourPriceRegion": "us-gov-west-1",
                "CanonicalName": "c3.2xlarge",
                "InstanceType": "c3.2xlarge",
                "Memory": 15360,
                "ModifiedDate": "2024-07-22 00:24:51",
                "PaymentType": "OnDemand",
                "PricePerHour": 0,
                "tags": []
            },
            {
                "Architecture": [
                    "x86_64"
                ],
                "BestOnDemandHourPriceRegion": "us-gov-west-1",
                "CanonicalName": "c4.2xlarge",
                "InstanceType": "c4.2xlarge",
                "Memory": 15360,
                "ModifiedDate": "2024-07-22 00:24:51",
                "PaymentType": "OnDemand",
                "PricePerHour": 0,
                "tags": []
            },
            {
                "Architecture": [
                    "x86_64"
                ],
                "BestOnDemandHourPriceRegion": "us-gov-west-1",
                "CanonicalName": "c5.2xlarge",
                "InstanceType": "c5.2xlarge",
                "Memory": 16384,
                "ModifiedDate": "2024-07-22 00:24:51",
                "PaymentType": "OnDemand",
                "PricePerHour": 0,
                "tags": []
            }
        ]
    }
}